mapling/__init__.py
mapling/main.py
mapling-0.1.1.dist-info/entry_points.txt
mapling-0.1.1.dist-info/WHEEL
mapling-0.1.1.dist-info/METADATA
mapling-0.1.1.dist-info/RECORD
