Metadata-Version: 2.1
Name: mapling
Version: 0.1.1
Summary: 
Author: Andrew Janco
Author-email: ajanco@haverford.edu
Requires-Python: >=3.5,<4.0
Classifier: Programming Language :: Python :: 3
Classifier: Programming Language :: Python :: 3.5
Classifier: Programming Language :: Python :: 3.6
Classifier: Programming Language :: Python :: 3.7
Classifier: Programming Language :: Python :: 3.8
Requires-Dist: pandas (>=1.0.3,<2.0.0)
Requires-Dist: requests (>=2.23.0,<3.0.0)
Requires-Dist: spacy (>=2.2.4,<3.0.0)
Requires-Dist: textract (>=1.6.3,<2.0.0)
Requires-Dist: typer[all] (>=0.1.1,<0.2.0)
